gcmap
