Metadata-Version: 1.0
Name: gcmap
Version: 0.0.2
Summary: Great circle visualization of many coordinate pairs
Home-page: https://github.com/paulgb/gcmap
Author: Paul Butler
Author-email: paulgb@gmail.com
License: UNKNOWN
Platform: UNKNOWN
